HTPy5/Webgets.py
HTPy5/__init__.py
HTPy5/__main__.py
HTPy5/Htools/__init__.py
HTPy5/Htools/Stylor/__init__.py
HTPy5-1.0.1.dist-info/LICENSE
HTPy5-1.0.1.dist-info/METADATA
HTPy5-1.0.1.dist-info/WHEEL
HTPy5-1.0.1.dist-info/top_level.txt
HTPy5-1.0.1.dist-info/RECORD
