Metadata-Version: 2.1
Name: HTPy5
Version: 1.0.1
Summary: This is HTPy5, a module for writing HTML using Python.
Author-email: BoodyWin Workshop <boodywin.studio.123@gmail.com>
Project-URL: Homepage, https://boodywin.github.io/HTPy5
Project-URL: Bug Tracker, https://github.com/BoodyWin/HTPy5/issues
Project-URL: Source Code, https://github.com/BoodyWin/HTPy5
Project-URL: Documentation, https://boodywin.github.io/HTPy5/docs
Project-URL: PyPI, https://pypi.org/project/HTPy5/
Project-URL: Terms of Use, https://boodywin.github.io/HTPy5/Privacy-and-Terms/#terms-of-use
Project-URL: Privacy Policy, https://boodywin.github.io/HTPy5/Privacy-and-Terms/#privacy-policy
Project-URL: License, https://boodywin.github.io/HTPy5/LICENSE.txt
Keywords: HTPy5,HTML5,PY2HTML,web development,HTML generation,Python to HTML
Classifier: Development Status :: 4 - Beta
Classifier: Intended Audience :: Developers
Classifier: License :: OSI Approved :: MIT License
Classifier: Programming Language :: Python :: 3
Classifier: Programming Language :: Python :: 3.6
Classifier: Programming Language :: Python :: 3.7
Classifier: Programming Language :: Python :: 3.8
Classifier: Programming Language :: Python :: 3.9
Classifier: Programming Language :: Python :: 3.10
Classifier: Programming Language :: Python :: 3.11
Classifier: Programming Language :: Python :: 3.12
Classifier: Programming Language :: Python :: 3.13
Requires-Python: >=3.6
License-File: LICENSE
